begetAPI/__answer.py
begetAPI/__init__.py
begetAPI/__request.py
begetAPI/__rest_api.py
begetAPI/backup.py
begetAPI/beget.py
begetAPI/cron.py
begetAPI/dns.py
begetAPI/domain.py
begetAPI/ftp.py
begetAPI/mail.py
begetAPI/mysql.py
begetAPI/site.py
begetAPI/stat.py
begetAPI/user.py
begetAPI-0.0.2.dist-info/LICENSE
begetAPI-0.0.2.dist-info/METADATA
begetAPI-0.0.2.dist-info/WHEEL
begetAPI-0.0.2.dist-info/top_level.txt
begetAPI-0.0.2.dist-info/RECORD
