Metadata-Version: 2.1
Name: begetAPI
Version: 0.0.2
Summary: Wrapper for Beget API
Home-page: https://github.com/cry0this/begetAPI
Download-URL: https://github.com/cry0this/begetAPI/archive/refs/tags/v0.0.2.tar.gz
Author: Alex Kiselev
Author-email: cry0this@gmail.com
License: GNU General Public License v3.0
Keywords: api,beget
Platform: UNKNOWN
Classifier: Development Status :: 4 - Beta
Classifier: Intended Audience :: Developers
Classifier: Operating System :: OS Independent
Classifier: License :: OSI Approved :: GNU General Public License v3 (GPLv3)
Classifier: Programming Language :: Python :: 3
Classifier: Programming Language :: Python :: 3.6
Classifier: Programming Language :: Python :: 3.7
Classifier: Programming Language :: Python :: 3.8
Classifier: Programming Language :: Python :: 3.9
Classifier: Programming Language :: Python :: 3.10
License-File: LICENSE
Requires-Dist: requests
Requires-Dist: aiohttp
